failbot/__init__.py
failbot/auth.py
failbot/cli.py
failbot/config.py
failbot/send.py
failbot/stream.py
failbot_cli-0.1.1.dist-info/licenses/LICENSE
failbot_cli-0.1.1.dist-info/METADATA
failbot_cli-0.1.1.dist-info/WHEEL
failbot_cli-0.1.1.dist-info/entry_points.txt
failbot_cli-0.1.1.dist-info/top_level.txt
failbot_cli-0.1.1.dist-info/RECORD
